fleur/__init__.py
fleur/barstats.py
fleur/betweenstats.py
fleur/scatterstats.py
fleur/_utils/__init__.py
fleur/_utils/beeswarm.py
fleur/_utils/count_decimals.py
fleur/_utils/infer_types.py
fleur/_utils/input_data_handling.py
fleur/_utils/theme.py
fleur/data/__init__.py
fleur/data/datasets.py
fleur/data/iris.csv
fleur/data/mtcars.csv
fleur/data/titanic.csv
fleur-0.0.4.dist-info/licenses/LICENSE
fleur-0.0.4.dist-info/METADATA
fleur-0.0.4.dist-info/WHEEL
fleur-0.0.4.dist-info/top_level.txt
fleur-0.0.4.dist-info/RECORD
