Metadata-Version: 2.4
Name: fleur
Version: 0.0.4
Summary: Combining statistics with visualization for Python
Author-email: Joseph Barbier <joseph.barbierdarnal@gmail.com>
License-Expression: MIT
Project-URL: Homepage, https://y-sunflower.github.io/fleur/
Project-URL: Issues, https://github.com/y-sunflower/fleur/issues
Project-URL: Documentation, https://y-sunflower.github.io/fleur/
Project-URL: Repository, https://github.com/y-sunflower/fleur
Keywords: statistics,visualization,data,annotations,reproductibility
Classifier: Programming Language :: Python :: 3
Classifier: Operating System :: OS Independent
Classifier: Development Status :: 3 - Alpha
Requires-Python: >=3.10
License-File: LICENSE
Requires-Dist: matplotlib>=3.10
Requires-Dist: narwhals>=1.41.0
Requires-Dist: scipy>=1.13.1
Dynamic: license-file
